straceexec.py
tests/__init__.py
tests/tests.py
straceexec-1.0.0.dist-info/LICENSE
straceexec-1.0.0.dist-info/METADATA
straceexec-1.0.0.dist-info/WHEEL
straceexec-1.0.0.dist-info/entry_points.txt
straceexec-1.0.0.dist-info/top_level.txt
straceexec-1.0.0.dist-info/RECORD
