Metadata-Version: 2.1
Name: straceexec
Version: 1.0.0
Summary: A tool for executing commands based on strace output
Home-page: https://github.com/dandedrick/straceexec
Author: Dan Dedrick
Author-email: dan.dedrick@gmail.com
License: UNKNOWN
Platform: UNKNOWN
Classifier: License :: OSI Approved :: MIT License
Classifier: Operating System :: POSIX :: Linux
Classifier: Topic :: Utilities
Classifier: Programming Language :: Python :: 2
Classifier: Programming Language :: Python :: 3
